MANIFEST.in
README.rst
json_nn.py
setup.cfg
setup.py
json_nn.egg-info/PKG-INFO
json_nn.egg-info/SOURCES.txt
json_nn.egg-info/dependency_links.txt
json_nn.egg-info/requires.txt
json_nn.egg-info/top_level.txt